[{"atccode":"A01AD","drug":"EPINEPHRINE","references":[{"reference_id":7,"reference_type":"pub","date":"2020-01-02T00:00:00.000"},{"reference_id":8,"reference_type":"pub","date":"2020-01-03T00:00:00.000"},{"reference_id":"NCT04188184","reference_type":"trial","date":"2020-04-27T00:00:00.000"},{"reference_id":"The journal of allergy and clinical immunology. In practice","reference_type":"journal","date":"2020-01-02T00:00:00.000"},{"reference_id":"The journal of allergy and clinical immunology. In practice","reference_type":"journal","date":"2020-01-03T00:00:00.000"},{"reference_id":"Journal of emergency nursing\\xc3\\x28","reference_type":"journal","date":"2020-04-27T00:00:00.000"}]},{"atccode":"A04AD","drug":"DIPHENHYDRAMINE","references":[{"reference_id":1,"reference_type":"pub","date":"2019-01-01T00:00:00.000"},{"reference_id":2,"reference_type":"pub","date":"2019-01-01T00:00:00.000"},{"reference_id":3,"reference_type":"pub","date":"2019-02-01T00:00:00.000"},{"reference_id":"NCT01967433","reference_type":"trial","date":"2020-01-01T00:00:00.000"},{"reference_id":"NCT04189588","reference_type":"trial","date":"2020-01-01T00:00:00.000"},{"reference_id":"NCT04237091","reference_type":"trial","date":"2020-01-01T00:00:00.000"},{"reference_id":"Journal of emergency nursing","reference_type":"journal","date":"2019-01-01T00:00:00.000"},{"reference_id":"The Journal of pediatrics","reference_type":"journal","date":"2019-02-01T00:00:00.000"},{"reference_id":"Journal of emergency nursing","reference_type":"journal","date":"2020-01-01T00:00:00.000"}]},{"atccode":"R01AD","drug":"BETAMETHASONE","references":[{"reference_id":"NCT04153396","reference_type":"trial","date":"2020-01-01T00:00:00.000"},{"reference_id":"H\u00f4pitaux Universitaires de Gen\u00e8ve","reference_type":"journal","date":"2020-01-01T00:00:00.000"}]},{"atccode":"S03AA","drug":"TETRACYCLINE","references":[{"reference_id":4,"reference_type":"pub","date":"2020-01-01T00:00:00.000"},{"reference_id":5,"reference_type":"pub","date":"2020-02-01T00:00:00.000"},{"reference_id":6,"reference_type":"pub","date":"2020-01-01T00:00:00.000"},{"reference_id":"Journal of food protection","reference_type":"journal","date":"2020-01-01T00:00:00.000"},{"reference_id":"American journal of veterinary research","reference_type":"journal","date":"2020-02-01T00:00:00.000"},{"reference_id":"Psychopharmacology","reference_type":"journal","date":"2020-01-01T00:00:00.000"}]},{"atccode":"V03AB","drug":"ETHANOL","references":[{"reference_id":6,"reference_type":"pub","date":"2020-01-01T00:00:00.000"},{"reference_id":"Psychopharmacology","reference_type":"journal","date":"2020-01-01T00:00:00.000"}]}]
